gshocktimeserver/__init__.py
gshocktimeserver/alarms.py
gshocktimeserver/api_tests.py
gshocktimeserver/args.py
gshocktimeserver/casio_constants.py
gshocktimeserver/configurator.py
gshocktimeserver/connection.py
gshocktimeserver/data_watcher.py
gshocktimeserver/event.py
gshocktimeserver/gshock_api.py
gshocktimeserver/gshock_server.py
gshocktimeserver/logger.py
gshocktimeserver/mailsener.py
gshocktimeserver/message_dispatcher.py
gshocktimeserver/result_queue.py
gshocktimeserver/scanner.py
gshocktimeserver/settings.py
gshocktimeserver/utils.py
gshocktimeserver/watch_info.py
gshocktimeserver/iolib/__init__.py
gshocktimeserver/iolib/alarms_io.py
gshocktimeserver/iolib/app_info_io.py
gshocktimeserver/iolib/button_pressed_io.py
gshocktimeserver/iolib/dst_for_world_cities_io.py
gshocktimeserver/iolib/dst_watch_state_io.py
gshocktimeserver/iolib/error_io.py
gshocktimeserver/iolib/events_io.py
gshocktimeserver/iolib/settings_io.py
gshocktimeserver/iolib/time_adjustement_io.py
gshocktimeserver/iolib/time_io.py
gshocktimeserver/iolib/timer_io.py
gshocktimeserver/iolib/unknown_io.py
gshocktimeserver/iolib/watch_condition_io.py
gshocktimeserver/iolib/watch_name_io.py
gshocktimeserver/iolib/world_cities_io.py
casiogshockapi-0.7.dist-info/LICENSE.txt
casiogshockapi-0.7.dist-info/METADATA
casiogshockapi-0.7.dist-info/WHEEL
casiogshockapi-0.7.dist-info/top_level.txt
casiogshockapi-0.7.dist-info/RECORD
