Metadata-Version: 2.1
Name: casiogshockapi
Version: 0.7
Summary: This library allows you to interact with your G-Shock watch from Python
Home-page: https://github.com/izivkov/GShockTimeServer
Author: Ivo Zivkov
Author-email: izivkov@gmail.com
License: MIT
Project-URL: Documentation, https://pyscaffold.org/
Platform: any
Classifier: Development Status :: 3 - Alpha
Classifier: Intended Audience :: Developers
Classifier: License :: OSI Approved :: MIT License
Classifier: Programming Language :: Python :: 3
Classifier: Programming Language :: Python :: 3.6
Classifier: Programming Language :: Python :: 3.7
Classifier: Programming Language :: Python :: 3.8
License-File: LICENSE.txt
Requires-Dist: bleak
Requires-Dist: pytz
Requires-Dist: reactivex
Provides-Extra: testing
Requires-Dist: pytest ; extra == 'testing'
Requires-Dist: pytest-cov ; extra == 'testing'
Requires-Dist: setuptools ; extra == 'testing'
